get_system_color/__init__.py
get_system_color/get_color.py
get_system_color-1.1.3.dist-info/LICENSE
get_system_color-1.1.3.dist-info/METADATA
get_system_color-1.1.3.dist-info/WHEEL
get_system_color-1.1.3.dist-info/top_level.txt
get_system_color-1.1.3.dist-info/RECORD
