Metadata-Version: 2.1
Name: get-system-color
Version: 1.1.3
Summary: 这个库可快速调用windows平台的主题色及主题的信号
Home-page: https://github.com/xiaoshuaiyo/get-system-color
Author: xiaoshuaiYo
Author-email: 619396351@qq.com
License: Apache2
Project-URL: Source Code, https://github.com/xiaoshuaiyo/get-system-color
Project-URL: Bug Tracker, https://github.com/xiaoshuaiyo/get-system-color/issues
License-File: LICENSE
